LICENSE.md
README.md
orbit_database_shell/__init__.py
orbit_database_shell/__main__.py
orbit_database_shell/odb_actions.py
orbit_database_shell/odb_completers.py
orbit_database_shell/odb_decorators.py
orbit_database_shell/odb_grammar.py
orbit_database_shell/odb_help.py
orbit_database_shell-1.0.28.dist-info/LICENSE.md
orbit_database_shell-1.0.28.dist-info/METADATA
orbit_database_shell-1.0.28.dist-info/WHEEL
orbit_database_shell-1.0.28.dist-info/entry_points.txt
orbit_database_shell-1.0.28.dist-info/RECORD
