Metadata-Version: 2.1
Name: orbit-database-shell
Version: 1.0.28
Summary: Orbit-DB Shell
Home-page: https://gitlab.com/madpenguin/orbit-database-shell
Keywords: database,shell
Author: Gareth Bult
Author-email: gareth@madpenguin.uk
Requires-Python: >=3.10,<4.0
Classifier: Development Status :: 4 - Beta
Classifier: Environment :: Console :: Curses
Classifier: Intended Audience :: Developers
Classifier: License :: OSI Approved :: MIT License
Classifier: Operating System :: OS Independent
Classifier: Programming Language :: Python :: 3
Classifier: Programming Language :: Python :: 3.10
Classifier: Programming Language :: Python :: 3.11
Classifier: Programming Language :: Python :: 3.12
Classifier: Topic :: Database :: Front-Ends
Classifier: Topic :: File Formats :: JSON
Requires-Dist: Pygments (>=2.12.0,<3.0.0)
Requires-Dist: loguru (>=0.7,<0.8)
Requires-Dist: mysql-connector-python (>=8.0.33,<9.0.0)
Requires-Dist: orbit-database (>=1.0.0)
Requires-Dist: prompt-toolkit
Requires-Dist: python-snappy (>=0.6.1,<0.7.0)
Requires-Dist: rich (>=13.3.4,<14.0.0)
Requires-Dist: termcolor (>=1.1.0,<2.0.0)
Requires-Dist: tqdm (>=4.65.0,<5.0.0)
Requires-Dist: ujson (>=5.4.0,<6.0.0)
Project-URL: Bug Tracker, https://gitlab.com/madpenguin/orbit-database-shell/-/issues
Project-URL: Documentation, https://gitlab.com/madpenguin/orbit-database-shell
Project-URL: Repository, https://gitlab.com/madpenguin/orbit-database-shell
